{"artists":[{"idArtist":"165169","strArtist":"Vernon Handley","strArtistStripped":null,"strArtistAlternate":"","strLabel":null,"idLabel":null,"intFormedYear":null,"intBornYear":"1930","intDiedYear":"2008","strDisbanded":null,"strStyle":"","strGenre":"Conductor","strMood":"","strWebsite":"","strFacebook":"","strTwitter":"1","strBiography":null,"strBiographyDE":"Vernon George Handley, CBE (* 11. November 1930, Enfield, London; \u2020 10. September 2008 in Monmouth, Monmouthshire, Wales) war ein englischer Dirigent. Als Sch\u00fcler von Sir Adrian Boult hat er sich insbesondere um die Pflege des britischen Repertoires klassischer Musik gro\u00dfe Verdienste erworben. \n\nHandley wurde als Sohn walisischer Eltern in eine musikalisch gebildete Familie geboren. Schon w\u00e4hrend seiner Schulzeit besuchte er die BBC Aufnahmestudios in Maida Vale und beobachtete dort seinen sp\u00e4teren Lehrmeister Boult bei der Arbeit. Nach Handleys eigenem Bekunden erlernte er so das R\u00fcstzeug dirigentischer Technik. In den fr\u00fchen 1950er Jahren korrespondierten beide schriftlich und trafen schlie\u00dflich 1958 pers\u00f6nlich aufeinander, nachdem Handley seinen Milit\u00e4rdienst beendet und das Studium am Balliol College, Oxford, abgeschlossen hatte. Er erinnert sich lebhaft an jene erste Begegnung: \u201eIm Verlaufe unseres Treffens drillte er mich in den schlimmsten zwei Stunden Kontrapunkt und Harmonielehre, die ich je erlebt hatte.\u201c\n\nIm Anschluss legte ihm Boult die Partitur einer Symphonie vor und fragte Handley, wie er eine bestimmte problematische Stelle darin l\u00f6sen w\u00fcrde. \u201eIch hatte Gl\u00fcck. Es war eine Seite aus Arnold Bax\u2019 Dritter Sinfonie, ein Werk, das ich in- und auswendig kannte.\u201c Handley l\u00f6ste das Problem zur Zufriedenheit des \u00e4lteren Dirigenten, der ihm daraufhin seine Unterst\u00fctzung zusagte. Bax\u2019 Dritte Sinfonie war es auch, die als zentrales Werk auf dem Programm von Handleys erstem \u00f6ffentlichen Konzert in London, mit dem Orchester des Merton College, stand. Handley war ein anerkannter Experte auf dem Gebiet der Musik gerade dieses englischen Sp\u00e4tromantikers, dessen vollst\u00e4ndige Symphonien und symphonische Dichtungen er sp\u00e4ter f\u00fcr die Compact Disc einspielte.\n\n1962 wurde Handley zum Chefdirigenten des jungen Guildford Philharmonic Orchestra ernannt, das er in den folgenden einundzwanzig Jahren leitete. Zugunsten dieser Aufgabe verzichtete Handley weitgehend auf eine internationale Karriere, was erkl\u00e4rt, warum er noch heute trotz seines umfassenden diskografischen Wirkens und der Bewunderung seiner Kollegen au\u00dferhalb Gro\u00dfbritanniens nur einem kleinen Kreis von Kennern bekannt ist. Neben Guildford baute Handley auch das Orchester von Tonbridge auf. 1983 schlie\u00dflich ernannte man ihn zum st\u00e4ndigen Gastdirigenten des London Philharmonic Orchestra. Ebenso leitete er das Amsterdam Philharmonic Orchestra (nicht zu verwechseln mit dem Concertgebouw-Orchester), das Ulster Orchestra in Belfast und war Ehrendirigent des Royal Liverpool Philharmonic Orchestra, einem der \u00e4ltesten Klangk\u00f6rper Gro\u00dfbritanniens. In zahlreichen Konzerten, Rundfunkaufnahmen und CD-Einspielungen dirigierte er mehrfach alle gro\u00dfen Londoner Orchester ebenso wie s\u00e4mtliche regionalen Orchester der BBC. Schallplattenfirmen, mit denen Vernon Handleys Karriere eng verbunden war, sind EMI, Chandos Records, Hyperion Records und zuletzt Dutton. Das Wiederaufleben des Spezialit\u00e4tenlabels Lyrita und die nachfolgende Ver\u00f6ffentlichung klassischer Aufnahmen aus den 1970er Jahren verschafften Handleys Wirken neue Aufmerksamkeit.\n\nIm Verlauf seiner f\u00fcnf Jahrzehnte umfassenden Karriere f\u00fchrte Handley zahllose Werke britischer Komponisten auf, darunter die Symphonien von Robert Simpson und Granville Bantock, die er ebenfalls \u2013 meist in Erstaufnahmen \u2013 einspielte. Zu seinen vielfach ausgezeichneten CD-Aufnahmen geh\u00f6ren unter anderem auch vollst\u00e4ndige Zyklen der Symphonien von Ralph Vaughan Williams, Malcolm Arnold und Charles Villiers Stanford, ebenso wie Werke von Edward Elgar, Arthur Bliss, Edgar Bainton, Alexander Mackenzie und York Bowen, dessen Instrumentalkonzerten besonders in den letzten Jahren Handleys Aufmerksamkeit gegolten hat.\n\nIn Anerkennung seiner Verdienste erhielt Handley am 3. Mai 2007 den Ehrenpreis der Classical BRIT Awards. Bereits 2004 hatte ihn die britische K\u00f6nigin Elisabeth II. zum \u201eCommander of the British Empire\u201c (CBE) ernannt.\n\nIm Januar 2007 wurde Handley zum Chefdirigenten des English Symphony Orchestra ernannt.\n\nAm 10. September 2008 starb Vernon Handley in seinem Haus in Monmouth. In seinen letzten Lebensjahren hatte er u. a. mit einer schweren Diabetes und den Folgen eines Verkehrsunfalls in M\u00fcnchen im Februar 2002 (bei dem der Fahrer seines Taxis starb) zu k\u00e4mpfen.\n(Wikipedia)","strBiographyFR":null,"strBiographyCN":null,"strBiographyIT":null,"strBiographyJP":null,"strBiographyRU":null,"strBiographyES":null,"strBiographyPT":null,"strBiographySE":null,"strBiographyNL":null,"strBiographyHU":null,"strBiographyNO":null,"strBiographyIL":null,"strBiographyPL":null,"strGender":"Male","intMembers":"1","strCountry":"","strCountryCode":"GB","strArtistThumb":null,"strArtistLogo":null,"strArtistCutout":null,"strArtistClearart":null,"strArtistWideThumb":null,"strArtistFanart":null,"strArtistFanart2":null,"strArtistFanart3":null,"strArtistFanart4":null,"strArtistBanner":null,"strMusicBrainzID":"10ab5755-ad56-4e85-a30f-ccfee81cf9d5","strISNIcode":null,"strLastFMChart":null,"intCharted":"0","strLocked":"unlocked"}]}