{"artists":[{"idArtist":"116054","strArtist":"Adam Rogers","strArtistStripped":null,"strArtistAlternate":"","strLabel":null,"idLabel":null,"intFormedYear":"1993","intBornYear":"1993","intDiedYear":null,"strDisbanded":null,"strStyle":"Rock/Pop","strGenre":"Jazz","strMood":null,"strWebsite":"","strFacebook":"","strTwitter":"1","strBiographyEN":"Adam Rogers is an American guitarist specializing in post bop, contemporary jazz, and classical music. Rogers has had a prolific and extensive session history as a recording guitarist having played on over 150 commercially released recordings. He is currently a member of the Chris Potter Underground in addition to leading his own \"acoustic\" jazz quartets and quintets as well as the genre bending electric trio DICE. He was a founding member and co leader of the eclectic group Lost Tribe. He has also performed and or recorded with Michael Brecker, Cassandra Wilson, Walter Becker, Norah Jones, John Patitucci, Paul Simon, John Zorn and Regina Carter among many others. He is a highly versatile player covering many areas of music but is best known for his work in the modern jazz idiom.","strBiographyDE":null,"strBiographyFR":null,"strBiographyCN":null,"strBiographyIT":null,"strBiographyJP":null,"strBiographyRU":null,"strBiographyES":null,"strBiographyPT":null,"strBiographySE":null,"strBiographyNL":null,"strBiographyHU":null,"strBiographyNO":null,"strBiographyIL":null,"strBiographyPL":null,"strGender":"Male","intMembers":"1","strCountry":"New York, USA","strCountryCode":"US","strArtistThumb":"https://www.theaudiodb.com/images/media/artist/thumb/strqsx1362599463.jpg","strArtistLogo":null,"strArtistCutout":null,"strArtistClearart":null,"strArtistWideThumb":null,"strArtistFanart":"https://www.theaudiodb.com/images/media/artist/fanart/vpxsvt1362599569.jpg","strArtistFanart2":null,"strArtistFanart3":null,"strArtistFanart4":null,"strArtistBanner":null,"strMusicBrainzID":"04e0d4e8-3450-4230-be98-d8f922374d0c","strISNIcode":null,"strLastFMChart":null,"intCharted":"3","strLocked":"unlocked"}]}