{"album":[{"idAlbum":"2127912","idArtist":"113972","idLabel":null,"strAlbum":"The Dark Side of the Chant","strAlbumStripped":"The Dark Side of the Chant","strArtist":"Gregorian","strArtistStripped":"Gregorian","intYearReleased":"2010","strStyle":"Rock/Pop","strGenre":"New Age","strLabel":null,"strReleaseFormat":"Album","intSales":"0","strAlbumThumb":"https://www.theaudiodb.com/images/media/album/thumb/vswtwx1363619169.jpg","strAlbumThumbHQ":null,"strAlbumThumbBack":null,"strAlbumCDart":"https://www.theaudiodb.com/images/media/album/cdart/the-dark-side-of-the-chant-534968b920ed5.png","strAlbumSpine":null,"strAlbum3DCase":null,"strAlbum3DFlat":null,"strAlbum3DFace":null,"strAlbum3DThumb":null,"strDescription":null,"strDescriptionDE":null,"strDescriptionFR":null,"strDescriptionCN":null,"strDescriptionIT":null,"strDescriptionJP":null,"strDescriptionRU":null,"strDescriptionES":null,"strDescriptionPT":null,"strDescriptionSE":null,"strDescriptionNL":null,"strDescriptionHU":null,"strDescriptionNO":null,"strDescriptionIL":null,"strDescriptionPL":null,"intLoved":null,"intScore":null,"intScoreVotes":null,"strReview":null,"strMood":"","strTheme":null,"strSpeed":null,"strLocation":null,"strMusicBrainzID":"2ed1e6d7-f64b-4206-b097-040a6e3ecdda","strMusicBrainzArtistID":"18a0d72d-0be0-4196-a340-035163bfae1c","strAllMusicID":null,"strBBCReviewID":null,"strRateYourMusicID":null,"strDiscogsID":null,"strWikidataID":null,"strWikipediaID":null,"strGeniusID":null,"strLyricWikiID":null,"strMusicMozID":null,"strItunesID":null,"strAmazonID":null,"strLocked":"unlocked"}]}