{"artists":[{"idArtist":"134788","strArtist":"Shu\u2022bi\u2022dua","strArtistStripped":null,"strArtistAlternate":null,"strLabel":null,"idLabel":null,"intFormedYear":"1973","intBornYear":"1973","intDiedYear":null,"strDisbanded":null,"strStyle":null,"strGenre":"","strMood":null,"strWebsite":null,"strFacebook":null,"strTwitter":null,"strBiographyEN":"The correct spelling of Shu-bi-dua.","strBiographyDE":null,"strBiographyFR":null,"strBiographyCN":null,"strBiographyIT":null,"strBiographyJP":null,"strBiographyRU":null,"strBiographyES":null,"strBiographyPT":null,"strBiographySE":null,"strBiographyNL":null,"strBiographyHU":null,"strBiographyNO":null,"strBiographyIL":null,"strBiographyPL":null,"strGender":null,"intMembers":null,"strCountry":null,"strCountryCode":"DK","strArtistThumb":"https://www.theaudiodb.com/images/media/artist/thumb/4788do1687879190.jpg","strArtistLogo":null,"strArtistCutout":null,"strArtistClearart":null,"strArtistWideThumb":null,"strArtistFanart":"https://www.theaudiodb.com/images/media/artist/fanart/rysrrr1422530837.jpg","strArtistFanart2":null,"strArtistFanart3":"https://www.theaudiodb.com/images/media/artist/fanart/fe0wul1687878944.jpg","strArtistFanart4":"https://www.theaudiodb.com/images/media/artist/fanart/vtmw8x1687879179.jpg","strArtistBanner":null,"strMusicBrainzID":"593a075e-b697-41c3-8cb5-3a8730958cfb","strISNIcode":null,"strLastFMChart":null,"intCharted":"4","strLocked":"unlocked"}]}